dmtoqt-1.0.0.dist-info/DESCRIPTION.rst
dmtoqt-1.0.0.dist-info/METADATA
dmtoqt-1.0.0.dist-info/RECORD
dmtoqt-1.0.0.dist-info/WHEEL
dmtoqt-1.0.0.dist-info/entry_points.txt
dmtoqt-1.0.0.dist-info/metadata.json
dmtoqt-1.0.0.dist-info/top_level.txt
src/ColorsParser.py
src/DMReader.py
src/EDMWidget.py
src/StackedEDMWidget.py
src/UIWriter.py
src/__init__.py
src/edmVarTypes.py
