Metadata-Version: 2.0
Name: dmtoqt
Version: 1.0.0
Summary: A tool for converting EDM displays to QT
Home-page: https://bitbucket.org/alscg/dmtoqt
Author: Lawrence Berkeley National Laboratory
Author-email: rfgunion@lbl.gov
License: EPICS Open License
Keywords: EPICS edm qt epicsqt caqtdm development
Platform: UNKNOWN
Classifier: Development Status :: 3 - Alpha
Classifier: Intended Audience :: Science/Research
Classifier: Operating System :: OS Independent
Classifier: Programming Language :: Python
Classifier: Topic :: Scientific/Engineering
Requires-Python: >=2.7
Provides-Extra: dev
Provides-Extra: test
